locasticsearch/__init__.py
locasticsearch/client/__init__.py
locasticsearch/client/indices.py
locasticsearch/helpers/__init__.py
locasticsearch/helpers/actions.py
locasticsearch-0.0.3.dist-info/LICENSE
locasticsearch-0.0.3.dist-info/WHEEL
locasticsearch-0.0.3.dist-info/METADATA
locasticsearch-0.0.3.dist-info/RECORD
