Metadata-Version: 2.1
Name: locasticsearch
Version: 0.0.3
Summary: Serverless full text search in Python
License: MIT
Author: Yaser Martinez
Author-email: yaser.martinez@gmail.com
Requires-Python: >=3.6.1,<4.0.0
Classifier: License :: OSI Approved :: MIT License
Classifier: Programming Language :: Python :: 3
Classifier: Programming Language :: Python :: 3.7
Classifier: Programming Language :: Python :: 3.8
